retrospect/__init__.py
retrospect/dis.py
retrospect-0.1.4.dist-info/DESCRIPTION.rst
retrospect-0.1.4.dist-info/METADATA
retrospect-0.1.4.dist-info/RECORD
retrospect-0.1.4.dist-info/WHEEL
retrospect-0.1.4.dist-info/metadata.json
retrospect-0.1.4.dist-info/top_level.txt
retrospect-0.1.4.dist-info/zip-safe
