Metadata-Version: 2.0
Name: retrospect
Version: 0.1.4
Summary: Log with 20/20 vision
Home-page: https://github.com/xtfxme/retrospect
Author: C Anthony Risinger
Author-email: UNKNOWN
License: BSD
Platform: UNKNOWN
Classifier: Development Status :: 3 - Alpha
Classifier: License :: OSI Approved :: BSD License
Classifier: Programming Language :: Python
Classifier: Intended Audience :: Developers
Requires-Dist: byteplay
